djseong/__init__.py
djseong/bar/__init__.py
djseong_test_bar-0.2.1.dist-info/METADATA
djseong_test_bar-0.2.1.dist-info/WHEEL
djseong_test_bar-0.2.1.dist-info/top_level.txt
djseong_test_bar-0.2.1.dist-info/RECORD
